[
  {
    "怪物名称等级": "普通坦克 1",
    "怪物编号": 3001,
    "等级": 1,
    "血量": 1310,
    "攻击力": 16.8,
    "攻速": 1,
    "攻击范围": 1,
    "移动速度": 1,
    "DPS": 5.6,
    "血量特效倍率": 0.2,
    "DPS特效倍率": 0,
    "战力": 196.4,
    "品质": "普通",
    "职业": "坦克",
    "名称": "普通坦克",
    "血量成长倍率": 1.6367,
    "攻击力成长倍率": 1.6367,
    "适配地图": "森林,草原,雪山",
    "对塔伤害": 20,
    "和理论值对比": 0.9995,
    "血量倍数": 10,
    "攻击力倍数": 3
  },
  {
    "怪物名称等级": "萨哈比精英坦克 1",
    "怪物编号": 3002,
    "等级": 1,
    "血量": 1670,
    "攻击力": 14.7,
    "攻速": 1.2,
    "攻击范围": 1.5,
    "移动速度": 1.2,
    "DPS": 6.321,
    "血量特效倍率": 0.5,
    "DPS特效倍率": 0,
    "战力": 294.747,
    "品质": "精英",
    "职业": "坦克",
    "名称": "萨哈比精英坦克",
    "血量成长倍率": 1.6367,
    "攻击力成长倍率": 1.6367,
    "适配地图": "森林,草原,雪山",
    "对塔伤害": 20,
    "和理论值对比": 1,
    "血量倍数": 10,
    "攻击力倍数": 3
  },
  {
    "怪物名称等级": "泰森 1",
    "怪物编号": 3003,
    "等级": 1,
    "血量": 1179,
    "攻击力": 33.6,
    "攻速": 1,
    "攻击范围": 1,
    "移动速度": 1,
    "DPS": 11.2,
    "血量特效倍率": 0,
    "DPS特效倍率": 0,
    "战力": 196.3,
    "品质": "普通",
    "职业": "近战",
    "名称": "泰森",
    "血量成长倍率": 1.6367,
    "攻击力成长倍率": 1.6367,
    "适配地图": "森林,草原,雪山",
    "对塔伤害": 20,
    "和理论值对比": 0.999,
    "血量倍数": 10,
    "攻击力倍数": 3
  },
  {
    "怪物名称等级": "残酷射手 1",
    "怪物编号": 3004,
    "等级": 1,
    "血量": 786,
    "攻击力": 30,
    "攻速": 1,
    "攻击范围": 3,
    "移动速度": 1.2,
    "DPS": 13,
    "血量特效倍率": 0,
    "DPS特效倍率": 0.3,
    "战力": 196.9,
    "品质": "普通",
    "职业": "远程",
    "名称": "残酷射手",
    "血量成长倍率": 1.6367,
    "攻击力成长倍率": 1.6367,
    "适配地图": "森林,草原,雪山",
    "对塔伤害": 20,
    "和理论值对比": 1.002,
    "血量倍数": 10,
    "攻击力倍数": 3
  },
  {
    "怪物名称等级": "刘易斯 1",
    "怪物编号": 3005,
    "等级": 1,
    "血量": 1200,
    "攻击力": 33.6,
    "攻速": 1,
    "攻击范围": 1,
    "移动速度": 1,
    "DPS": 11.2,
    "血量特效倍率": 0,
    "DPS特效倍率": 0,
    "战力": 198.4,
    "品质": "精英",
    "职业": "近战",
    "名称": "刘易斯",
    "血量成长倍率": 1.6367,
    "攻击力成长倍率": 1.6367,
    "适配地图": "森林,草原,雪山",
    "对塔伤害": 20,
    "和理论值对比": 0.6731,
    "血量倍数": 10,
    "攻击力倍数": 3
  },
  {
    "怪物名称等级": "精射手 1",
    "怪物编号": 3006,
    "等级": 1,
    "血量": 900,
    "攻击力": 48,
    "攻速": 1,
    "攻击范围": 3,
    "移动速度": 1,
    "DPS": 20.8,
    "血量特效倍率": 0,
    "DPS特效倍率": 0,
    "战力": 235.6,
    "品质": "精英",
    "职业": "远程",
    "名称": "精射手",
    "血量成长倍率": 1.6367,
    "攻击力成长倍率": 1.6367,
    "适配地图": "森林,草原,雪山",
    "对塔伤害": 20,
    "和理论值对比": 0.7993,
    "血量倍数": 10,
    "攻击力倍数": 3
  },
  {
    "怪物名称等级": "垃圾刺客 1",
    "怪物编号": 3007,
    "等级": 1,
    "血量": 700,
    "攻击力": 45,
    "攻速": 1,
    "攻击范围": 1,
    "移动速度": 2,
    "DPS": 15,
    "血量特效倍率": 0,
    "DPS特效倍率": 0,
    "战力": 175,
    "品质": "精英",
    "职业": "刺客",
    "名称": "垃圾刺客",
    "血量成长倍率": 1.6367,
    "攻击力成长倍率": 1.6367,
    "适配地图": "森林,草原,雪山",
    "对塔伤害": 20,
    "和理论值对比": 0.5937,
    "血量倍数": 10,
    "攻击力倍数": 3
  },
  {
    "怪物名称等级": "影流之主 1",
    "怪物编号": 3008,
    "等级": 1,
    "血量": 900,
    "攻击力": 48,
    "攻速": 1,
    "攻击范围": 1,
    "移动速度": 2.5,
    "DPS": 16,
    "血量特效倍率": 0,
    "DPS特效倍率": 0,
    "战力": 202,
    "品质": "普通",
    "职业": "刺客",
    "名称": "影流之主",
    "血量成长倍率": 1.6367,
    "攻击力成长倍率": 1.6367,
    "适配地图": "森林,草原,雪山",
    "对塔伤害": 20,
    "和理论值对比": 1.028,
    "血量倍数": 10,
    "攻击力倍数": 3
  }
]